notifications/__init__.py
notifications/apps.py
notifications/consumers.py
notifications/default_settings.py
notifications/fields.py
notifications/models.py
notifications/routing.py
notifications/tasks.py
notifications/utils.py
notifications/backends/__init__.py
notifications/backends/aws_sqs_lambda.py
notifications/backends/base.py
notifications/backends/celery.py
notifications/backends/django_channels.py
notifications/backends/rq.py
notifications/backends/synchronous.py
notifications/channels/__init__.py
notifications/channels/base.py
notifications/channels/console.py
notifications/channels/django_channels.py
notifications/migrations/0001_initial.py
notifications/migrations/0001_squashed_0010_notification_channels.py
notifications/migrations/0002_auto_20170718_1539.py
notifications/migrations/0002_django_jsonfield_backport.py
notifications/migrations/0003_auto_20170719_1137.py
notifications/migrations/0003_notification_channels_json.py
notifications/migrations/0004_auto_20170719_1138.py
notifications/migrations/0004_drop_channels.py
notifications/migrations/0005_auto_20170814_1118.py
notifications/migrations/0005_rename_channels_json_to_channels.py
notifications/migrations/0006_auto_20171005_0402.py
notifications/migrations/0006_rename_obj_to_object_id.py
notifications/migrations/0007_add_content_type_fields.py
notifications/migrations/0007_auto_20171006_0126.py
notifications/migrations/0008_auto_20210920_0149.py
notifications/migrations/0008_notification_extra_data.py
notifications/migrations/0009_auto_20180112_0915.py
notifications/migrations/0010_notification_channels.py
notifications/migrations/__init__.py
notifications/providers/__init__.py
notifications/providers/base.py
notifications/providers/console.py
notifications/providers/django_channels.py
notifications/providers/django_sms.py
notifications/providers/email.py
notifications/providers/fcm_web.py
notifications/providers/pusher_channels.py
notifications/providers/slack.py
django_notifs-4.0.0.dist-info/LICENSE
django_notifs-4.0.0.dist-info/METADATA
django_notifs-4.0.0.dist-info/WHEEL
django_notifs-4.0.0.dist-info/top_level.txt
django_notifs-4.0.0.dist-info/RECORD
