Metadata-Version: 2.1
Name: django-notifs
Version: 4.0.0
Summary: Modular notifications for Django
Home-page: https://github.com/danidee10/django-notifs
Author: Osaetin Daniel
Author-email: osaetindaniel@gmail.com
License: MIT
Platform: UNKNOWN
Requires-Python: >=3.6.0
License-File: LICENSE
Requires-Dist: django (>=2.2)
Requires-Dist: requests (>=2.25.1)
Requires-Dist: django-jsonfield-backport (>=1.0.4)
Provides-Extra: anymail
Requires-Dist: django-anymail (>=8.4) ; extra == 'anymail'
Provides-Extra: celery
Requires-Dist: celery (>=4.1.0) ; extra == 'celery'
Provides-Extra: channels
Requires-Dist: channels (>=3.0.3) ; extra == 'channels'
Requires-Dist: channels-redis (>=3.2.0) ; extra == 'channels'
Provides-Extra: pusher_channels
Requires-Dist: pusher (>=3.0.0) ; extra == 'pusher_channels'
Provides-Extra: rq
Requires-Dist: django-rq (>=2.4.0) ; extra == 'rq'
Provides-Extra: slack
Requires-Dist: slack-sdk (>=3.11.2) ; extra == 'slack'
Provides-Extra: sms
Requires-Dist: django-sms (>=0.5.0) ; extra == 'sms'
Provides-Extra: sqs_lambda
Requires-Dist: boto3 (>=1.18.48) ; extra == 'sqs_lambda'
